{"id": "tF7ZkPewwQo", "title": "Orquesta Aragon Medley: El Bodeguero / Chaleco / Sabrosona / Al Vaiven de Mi Carreta / Los...", "formats": [{"asr": 48000, "filesize": 27676473, "format_id": "249", "format_note": "tiny", "fps": null, "height": null, "quality": 0, "tbr": 49.048, "url": "https://rr2---sn-0opoxu-ihv6.googlevideo.com/videoplayback?expire=1670705620&ei=dJ2UY5K0GczCkwbisZKoCA&ip=189.173.225.87&id=o-AGRflb0DCW1x_jnc6XSKjQl4TLRiEQbTQ4W8ZZEJG5MN&itag=249&source=youtube&requiressl=yes&mh=U4&mm=31%2C29&mn=sn-0opoxu-ihv6%2Csn-q4flrnez&ms=au%2Crdu&mv=m&mvi=2&pl=24&gcr=mx&initcwndbps=888750&vprv=1&mime=audio%2Fwebm&ns=Yg5JUhqLY5KMBKDaV1hgA6sJ&gir=yes&clen=27676473&dur=4514.161&lmt=1614557088410254&mt=1670683760&fvip=3&keepalive=yes&fexp=24001373%2C24007246&beids=24432632&c=WEB&txp=5432434&n=De6OCzL7fIn8o-l_9&sparams=expire%2Cei%2Cip%2Cid%2Citag%2Csource%2Crequiressl%2Cgcr%2Cvprv%2Cmime%2Cns%2Cgir%2Cclen%2Cdur%2Clmt&lsparams=mh%2Cmm%2Cmn%2Cms%2Cmv%2Cmvi%2Cpl%2Cinitcwndbps&lsig=AG3C_xAwRAIgCSpIfPdAVoXClzenRQM91JT-rtHUhI0CRKnWe-FHYI4CICO7oQk_zuHK_kqqoGUWIIIuI44hU8UaGxYmxDmlIjl5&sig=AOq0QJ8wRQIhAOWE3uok54yluSq0eY9CIwZ5MZhpedqBNtysIpEGvr2RAiA6fZzcVDsZqs7cZhwJrOhWNsdYpUAErQPxJXp_lPLvUQ==", "width": null, "ext": "webm", "vcodec": "none", "acodec": "opus", "abr": 49.048, "downloader_options": {"http_chunk_size": 10485760}, "container": "webm_dash", "format": "249 - audio only (tiny)", "protocol": "https", "http_headers": {"User-Agent": "Mozilla/5.0 (Windows NT 10.0; Win64; x64) AppleWebKit/537.36 (KHTML, like Gecko) Chrome/75.0.3757.0 Safari/537.36", "Accept-Charset": "ISO-8859-1,utf-8;q=0.7,*;q=0.7", "Accept": "text/html,application/xhtml+xml,application/xml;q=0.9,*/*;q=0.8", "Accept-Encoding": "gzip, deflate", "Accept-Language": "en-us,en;q=0.5"}}, {"asr": 48000, "filesize": 35464320, "format_id": "250", "format_note": "tiny", "fps": null, "height": null, "quality": 0, "tbr": 62.849, "url": "https://rr2---sn-0opoxu-ihv6.googlevideo.com/videoplayback?expire=1670705620&ei=dJ2UY5K0GczCkwbisZKoCA&ip=189.173.225.87&id=o-AGRflb0DCW1x_jnc6XSKjQl4TLRiEQbTQ4W8ZZEJG5MN&itag=250&source=youtube&requiressl=yes&mh=U4&mm=31%2C29&mn=sn-0opoxu-ihv6%2Csn-q4flrnez&ms=au%2Crdu&mv=m&mvi=2&pl=24&gcr=mx&initcwndbps=888750&vprv=1&mime=audio%2Fwebm&ns=Yg5JUhqLY5KMBKDaV1hgA6sJ&gir=yes&clen=35464320&dur=4514.161&lmt=1614557090195512&mt=1670683760&fvip=3&keepalive=yes&fexp=24001373%2C24007246&beids=24432632&c=WEB&txp=5432434&n=De6OCzL7fIn8o-l_9&sparams=expire%2Cei%2Cip%2Cid%2Citag%2Csource%2Crequiressl%2Cgcr%2Cvprv%2Cmime%2Cns%2Cgir%2Cclen%2Cdur%2Clmt&lsparams=mh%2Cmm%2Cmn%2Cms%2Cmv%2Cmvi%2Cpl%2Cinitcwndbps&lsig=AG3C_xAwRAIgEU1AJgc6bBm1ckDrzWNeojct9Ho33CA_8gKGU53H1WUCIE44ETq8Nf68ll8YsI3TIez8CNiDxXVGvHfd97gPRE6c&sig=AOq0QJ8wRAIgTFPnBlu7YOP6ypE6xtpjFRrlSdOfq80qL01ZMDVPwfACIBtH5y3NqT9e8ONT-cJBaG5qYPwZSSLpyxbORggKdz7V", "width": null, "ext": "webm", "vcodec": "none", "acodec": "opus", "abr": 62.849, "downloader_options": {"http_chunk_size": 10485760}, "container": "webm_dash", "format": "250 - audio only (tiny)", "protocol": "https", "http_headers": {"User-Agent": "Mozilla/5.0 (Windows NT 10.0; Win64; x64) AppleWebKit/537.36 (KHTML, like Gecko) Chrome/75.0.3757.0 Safari/537.36", "Accept-Charset": "ISO-8859-1,utf-8;q=0.7,*;q=0.7", "Accept": "text/html,application/xhtml+xml,application/xml;q=0.9,*/*;q=0.8", "Accept-Encoding": "gzip, deflate", "Accept-Language": "en-us,en;q=0.5"}}, {"asr": 48000, "filesize": 65968749, "format_id": "251", "format_note": "tiny", "fps": null, "height": null, "quality": 0, "tbr": 116.909, "url": "https://rr2---sn-0opoxu-ihv6.googlevideo.com/videoplayback?expire=1670705620&ei=dJ2UY5K0GczCkwbisZKoCA&ip=189.173.225.87&id=o-AGRflb0DCW1x_jnc6XSKjQl4TLRiEQbTQ4W8ZZEJG5MN&itag=251&source=youtube&requiressl=yes&mh=U4&mm=31%2C29&mn=sn-0opoxu-ihv6%2Csn-q4flrnez&ms=au%2Crdu&mv=m&mvi=2&pl=24&gcr=mx&initcwndbps=888750&vprv=1&mime=audio%2Fwebm&ns=Yg5JUhqLY5KMBKDaV1hgA6sJ&gir=yes&clen=65968749&dur=4514.161&lmt=1614557227646157&mt=1670683760&fvip=3&keepalive=yes&fexp=24001373%2C24007246&beids=24432632&c=WEB&txp=5432434&n=De6OCzL7fIn8o-l_9&sparams=expire%2Cei%2Cip%2Cid%2Citag%2Csource%2Crequiressl%2Cgcr%2Cvprv%2Cmime%2Cns%2Cgir%2Cclen%2Cdur%2Clmt&lsparams=mh%2Cmm%2Cmn%2Cms%2Cmv%2Cmvi%2Cpl%2Cinitcwndbps&lsig=AG3C_xAwRQIhALvfMQUg9477VopmCagmyoF3x7h52RaZiB5dO98j-XaFAiB0t3lTlcmsGB8ktSG_tdcYnM-o1fuVuGWsM0kezT8C9w%3D%3D&sig=AOq0QJ8wRQIhAI1JcORZkOOlMKiLdea-KR8Le_JqqU5p_pCVJNORCtKhAiB-a73JLykocR653OcJahLfCeq4J3767hKA4mBqGqA1TQ==", "width": null, "ext": "webm", "vcodec": "none", "acodec": "opus", "abr": 116.909, "downloader_options": {"http_chunk_size": 10485760}, "container": "webm_dash", "format": "251 - audio only (tiny)", "protocol": "https", "http_headers": {"User-Agent": "Mozilla/5.0 (Windows NT 10.0; Win64; x64) AppleWebKit/537.36 (KHTML, like Gecko) Chrome/75.0.3757.0 Safari/537.36", "Accept-Charset": "ISO-8859-1,utf-8;q=0.7,*;q=0.7", "Accept": "text/html,application/xhtml+xml,application/xml;q=0.9,*/*;q=0.8", "Accept-Encoding": "gzip, deflate", "Accept-Language": "en-us,en;q=0.5"}}, {"asr": 44100, "filesize": 73058146, "format_id": "140", "format_note": "tiny", "fps": null, "height": null, "quality": 0, "tbr": 129.474, "url": "https://rr2---sn-0opoxu-ihv6.googlevideo.com/videoplayback?expire=1670705620&ei=dJ2UY5K0GczCkwbisZKoCA&ip=189.173.225.87&id=o-AGRflb0DCW1x_jnc6XSKjQl4TLRiEQbTQ4W8ZZEJG5MN&itag=140&source=youtube&requiressl=yes&mh=U4&mm=31%2C29&mn=sn-0opoxu-ihv6%2Csn-q4flrnez&ms=au%2Crdu&mv=m&mvi=2&pl=24&gcr=mx&initcwndbps=888750&vprv=1&mime=audio%2Fmp4&ns=Yg5JUhqLY5KMBKDaV1hgA6sJ&gir=yes&clen=73058146&dur=4514.142&lmt=1614557616303038&mt=1670683760&fvip=3&keepalive=yes&fexp=24001373%2C24007246&beids=24432632&c=WEB&txp=5432434&n=De6OCzL7fIn8o-l_9&sparams=expire%2Cei%2Cip%2Cid%2Citag%2Csource%2Crequiressl%2Cgcr%2Cvprv%2Cmime%2Cns%2Cgir%2Cclen%2Cdur%2Clmt&lsparams=mh%2Cmm%2Cmn%2Cms%2Cmv%2Cmvi%2Cpl%2Cinitcwndbps&lsig=AG3C_xAwRgIhAJzlgrgkHTroIZFk4ZYyyDIZwVAXTMJ9Yuh4o-QIzGCHAiEA5bZnCeCSm7KoXKdTS91vD-pd48pL5S1wUgE6gKppT7A%3D&sig=AOq0QJ8wRAIgJSRCSqzlw4oGPtd5ekJt0TfzPJ2Seev6I0eGT4M0sUYCIAvLRCld1xH4dCqrbY_xZrhJHUR1xstwoMR6grHRzcfv", "width": null, "ext": "m4a", "vcodec": "none", "acodec": "mp4a.40.2", "abr": 129.474, "downloader_options": {"http_chunk_size": 10485760}, "container": "m4a_dash", "format": "140 - audio only (tiny)", "protocol": "https", "http_headers": {"User-Agent": "Mozilla/5.0 (Windows NT 10.0; Win64; x64) AppleWebKit/537.36 (KHTML, like Gecko) Chrome/75.0.3757.0 Safari/537.36", "Accept-Charset": "ISO-8859-1,utf-8;q=0.7,*;q=0.7", "Accept": "text/html,application/xhtml+xml,application/xml;q=0.9,*/*;q=0.8", "Accept-Encoding": "gzip, deflate", "Accept-Language": "en-us,en;q=0.5"}}, {"asr": null, "filesize": 4792544, "format_id": "160", "format_note": "144p", "fps": 25, "height": 144, "quality": 0, "tbr": 8.493, "url": "https://rr2---sn-0opoxu-ihv6.googlevideo.com/videoplayback?expire=1670705620&ei=dJ2UY5K0GczCkwbisZKoCA&ip=189.173.225.87&id=o-AGRflb0DCW1x_jnc6XSKjQl4TLRiEQbTQ4W8ZZEJG5MN&itag=160&aitags=133%2C134%2C135%2C136%2C137%2C160%2C242%2C243%2C244%2C247%2C248%2C278%2C394%2C395%2C396%2C397%2C398%2C399&source=youtube&requiressl=yes&mh=U4&mm=31%2C29&mn=sn-0opoxu-ihv6%2Csn-q4flrnez&ms=au%2Crdu&mv=m&mvi=2&pl=24&gcr=mx&initcwndbps=888750&vprv=1&mime=video%2Fmp4&ns=Yg5JUhqLY5KMBKDaV1hgA6sJ&gir=yes&clen=4792544&dur=4514.120&lmt=1614557595749514&mt=1670683760&fvip=3&keepalive=yes&fexp=24001373%2C24007246&beids=24432632&c=WEB&txp=5432434&n=De6OCzL7fIn8o-l_9&sparams=expire%2Cei%2Cip%2Cid%2Caitags%2Csource%2Crequiressl%2Cgcr%2Cvprv%2Cmime%2Cns%2Cgir%2Cclen%2Cdur%2Clmt&lsparams=mh%2Cmm%2Cmn%2Cms%2Cmv%2Cmvi%2Cpl%2Cinitcwndbps&lsig=AG3C_xAwRQIhALR9N3WTjY4pytsyc2JEDEoGkaIuFxxfDixHSmOqDZu1AiAkL7bBsigI4URnX4O2tJK7uxnunm93mdNoVy_sgRMSog%3D%3D&sig=AOq0QJ8wRAIgZi7Tum5Q-OiG_THy90DeLNl68TjnpJdoNU5fmmAyTpgCICp6ksqcjAvaJCKQmiOgYv_lJDavgfJZyK1K1R6d61IW", "width": 144, "ext": "mp4", "vcodec": "avc1.4d400b", "acodec": "none", "vbr": 8.493, "downloader_options": {"http_chunk_size": 10485760}, "container": "mp4_dash", "format": "160 - 144x144 (144p)", "protocol": "https", "http_headers": {"User-Agent": "Mozilla/5.0 (Windows NT 10.0; Win64; x64) AppleWebKit/537.36 (KHTML, like Gecko) Chrome/75.0.3757.0 Safari/537.36", "Accept-Charset": "ISO-8859-1,utf-8;q=0.7,*;q=0.7", "Accept": "text/html,application/xhtml+xml,application/xml;q=0.9,*/*;q=0.8", "Accept-Encoding": "gzip, deflate", "Accept-Language": "en-us,en;q=0.5"}}, {"asr": null, "filesize": 9273759, "format_id": "278", "format_note": "144p", "fps": 25, "height": 144, "quality": 0, "tbr": 16.435, "url": "https://rr2---sn-0opoxu-ihv6.googlevideo.com/videoplayback?expire=1670705620&ei=dJ2UY5K0GczCkwbisZKoCA&ip=189.173.225.87&id=o-AGRflb0DCW1x_jnc6XSKjQl4TLRiEQbTQ4W8ZZEJG5MN&itag=278&aitags=133%2C134%2C135%2C136%2C137%2C160%2C242%2C243%2C244%2C247%2C248%2C278%2C394%2C395%2C396%2C397%2C398%2C399&source=youtube&requiressl=yes&mh=U4&mm=31%2C29&mn=sn-0opoxu-ihv6%2Csn-q4flrnez&ms=au%2Crdu&mv=m&mvi=2&pl=24&gcr=mx&initcwndbps=888750&vprv=1&mime=video%2Fwebm&ns=Yg5JUhqLY5KMBKDaV1hgA6sJ&gir=yes&clen=9273759&dur=4514.120&lmt=1614558029265339&mt=1670683760&fvip=3&keepalive=yes&fexp=24001373%2C24007246&beids=24432632&c=WEB&txp=5432434&n=De6OCzL7fIn8o-l_9&sparams=expire%2Cei%2Cip%2Cid%2Caitags%2Csource%2Crequiressl%2Cgcr%2Cvprv%2Cmime%2Cns%2Cgir%2Cclen%2Cdur%2Clmt&lsparams=mh%2Cmm%2Cmn%2Cms%2Cmv%2Cmvi%2Cpl%2Cinitcwndbps&lsig=AG3C_xAwRAIgEQHpw-UXq3wZypBEU07ARiGU0fYp4hnzjN1-MCWhTIQCIC78LQcJmibauqUlxDZP15zL9L9WTai78DfM07LndWJj&sig=AOq0QJ8wRQIge_twIk_aVfgCCq6uhKGLmdIoQzYAEfGB4f-B9CdVMuUCIQDMx6n5Yj09MJGhCJ3eTK8SEi0ophAfbaXjHQw7g32_qw==", "width": 144, "ext": "webm", "vcodec": "vp9", "acodec": "none", "vbr": 16.435, "downloader_options": {"http_chunk_size": 10485760}, "container": "webm_dash", "format": "278 - 144x144 (144p)", "protocol": "https", "http_headers": {"User-Agent": "Mozilla/5.0 (Windows NT 10.0; Win64; x64) AppleWebKit/537.36 (KHTML, like Gecko) Chrome/75.0.3757.0 Safari/537.36", "Accept-Charset": "ISO-8859-1,utf-8;q=0.7,*;q=0.7", "Accept": "text/html,application/xhtml+xml,application/xml;q=0.9,*/*;q=0.8", "Accept-Encoding": "gzip, deflate", "Accept-Language": "en-us,en;q=0.5"}}, {"asr": null, "filesize": 10085945, "format_id": "394", "format_note": "144p", "fps": 25, "height": 144, "quality": 0, "tbr": 17.874, "url": "https://rr2---sn-0opoxu-ihv6.googlevideo.com/videoplayback?expire=1670705620&ei=dJ2UY5K0GczCkwbisZKoCA&ip=189.173.225.87&id=o-AGRflb0DCW1x_jnc6XSKjQl4TLRiEQbTQ4W8ZZEJG5MN&itag=394&aitags=133%2C134%2C135%2C136%2C137%2C160%2C242%2C243%2C244%2C247%2C248%2C278%2C394%2C395%2C396%2C397%2C398%2C399&source=youtube&requiressl=yes&mh=U4&mm=31%2C29&mn=sn-0opoxu-ihv6%2Csn-q4flrnez&ms=au%2Crdu&mv=m&mvi=2&pl=24&gcr=mx&initcwndbps=888750&vprv=1&mime=video%2Fmp4&ns=Yg5JUhqLY5KMBKDaV1hgA6sJ&gir=yes&clen=10085945&dur=4514.120&lmt=1615882728921315&mt=1670683760&fvip=3&keepalive=yes&fexp=24001373%2C24007246&beids=24432632&c=WEB&txp=5436432&n=De6OCzL7fIn8o-l_9&sparams=expire%2Cei%2Cip%2Cid%2Caitags%2Csource%2Crequiressl%2Cgcr%2Cvprv%2Cmime%2Cns%2Cgir%2Cclen%2Cdur%2Clmt&lsparams=mh%2Cmm%2Cmn%2Cms%2Cmv%2Cmvi%2Cpl%2Cinitcwndbps&lsig=AG3C_xAwRgIhAK-7bxa_eM37AA-ZyUOxeSwM1tI5kfkfT9E_KWgg5eOjAiEA7rH_jaWN-WqG3Noc-SHIOubv9fE4eHh3r8Zw5IlQEks%3D&sig=AOq0QJ8wRQIhAIG8CSqGvQ5ydz3uzCt6cGvo1GVxlxUtF_b3PPbw01xHAiBJIH3ncGcMFUsgZZAhCtb9GhsXW2U4q2rwEDaaEpTblQ==", "width": 144, "ext": "mp4", "vcodec": "av01.0.00M.08", "acodec": "none", "vbr": 17.874, "downloader_options": {"http_chunk_size": 10485760}, "container": "mp4_dash", "format": "394 - 144x144 (144p)", "protocol": "https", "http_headers": {"User-Agent": "Mozilla/5.0 (Windows NT 10.0; Win64; x64) AppleWebKit/537.36 (KHTML, like Gecko) Chrome/75.0.3757.0 Safari/537.36", "Accept-Charset": "ISO-8859-1,utf-8;q=0.7,*;q=0.7", "Accept": "text/html,application/xhtml+xml,application/xml;q=0.9,*/*;q=0.8", "Accept-Encoding": "gzip, deflate", "Accept-Language": "en-us,en;q=0.5"}}, {"asr": null, "filesize": 6896950, "format_id": "133", "format_note": "240p", "fps": 25, "height": 240, "quality": 1, "tbr": 12.222, "url": "https://rr2---sn-0opoxu-ihv6.googlevideo.com/videoplayback?expire=1670705620&ei=dJ2UY5K0GczCkwbisZKoCA&ip=189.173.225.87&id=o-AGRflb0DCW1x_jnc6XSKjQl4TLRiEQbTQ4W8ZZEJG5MN&itag=133&aitags=133%2C134%2C135%2C136%2C137%2C160%2C242%2C243%2C244%2C247%2C248%2C278%2C394%2C395%2C396%2C397%2C398%2C399&source=youtube&requiressl=yes&mh=U4&mm=31%2C29&mn=sn-0opoxu-ihv6%2Csn-q4flrnez&ms=au%2Crdu&mv=m&mvi=2&pl=24&gcr=mx&initcwndbps=888750&vprv=1&mime=video%2Fmp4&ns=Yg5JUhqLY5KMBKDaV1hgA6sJ&gir=yes&clen=6896950&dur=4514.120&lmt=1614557586326722&mt=1670683760&fvip=3&keepalive=yes&fexp=24001373%2C24007246&beids=24432632&c=WEB&txp=5432434&n=De6OCzL7fIn8o-l_9&sparams=expire%2Cei%2Cip%2Cid%2Caitags%2Csource%2Crequiressl%2Cgcr%2Cvprv%2Cmime%2Cns%2Cgir%2Cclen%2Cdur%2Clmt&lsparams=mh%2Cmm%2Cmn%2Cms%2Cmv%2Cmvi%2Cpl%2Cinitcwndbps&lsig=AG3C_xAwRQIgC3jjKUlkevaAJX7yCmRL47l0EUKKyEJi8dQvCcnkI1sCIQCtGBSIgeE5BJBnsjDPHTl1lprduBWUVigSDLRsPARcgw%3D%3D&sig=AOq0QJ8wRAIgY_NnhoG8Edf_Txyl2llDi_aFatqvTHbnlpzgiRE84pMCIBOMA66Zn_T22Qv0_XkBloHt2VURkU84PB-dIhAwZOd2", "width": 240, "ext": "mp4", "vcodec": "avc1.4d400c", "acodec": "none", "vbr": 12.222, "downloader_options": {"http_chunk_size": 10485760}, "container": "mp4_dash", "format": "133 - 240x240 (240p)", "protocol": "https", "http_headers": {"User-Agent": "Mozilla/5.0 (Windows NT 10.0; Win64; x64) AppleWebKit/537.36 (KHTML, like Gecko) Chrome/75.0.3757.0 Safari/537.36", "Accept-Charset": "ISO-8859-1,utf-8;q=0.7,*;q=0.7", "Accept": "text/html,application/xhtml+xml,application/xml;q=0.9,*/*;q=0.8", "Accept-Encoding": "gzip, deflate", "Accept-Language": "en-us,en;q=0.5"}}, {"asr": null, "filesize": 9617211, "format_id": "395", "format_note": "240p", "fps": 25, "height": 240, "quality": 1, "tbr": 17.043, "url": "https://rr2---sn-0opoxu-ihv6.googlevideo.com/videoplayback?expire=1670705620&ei=dJ2UY5K0GczCkwbisZKoCA&ip=189.173.225.87&id=o-AGRflb0DCW1x_jnc6XSKjQl4TLRiEQbTQ4W8ZZEJG5MN&itag=395&aitags=133%2C134%2C135%2C136%2C137%2C160%2C242%2C243%2C244%2C247%2C248%2C278%2C394%2C395%2C396%2C397%2C398%2C399&source=youtube&requiressl=yes&mh=U4&mm=31%2C29&mn=sn-0opoxu-ihv6%2Csn-q4flrnez&ms=au%2Crdu&mv=m&mvi=2&pl=24&gcr=mx&initcwndbps=888750&vprv=1&mime=video%2Fmp4&ns=Yg5JUhqLY5KMBKDaV1hgA6sJ&gir=yes&clen=9617211&dur=4514.120&lmt=1615882733254661&mt=1670683760&fvip=3&keepalive=yes&fexp=24001373%2C24007246&beids=24432632&c=WEB&txp=5436432&n=De6OCzL7fIn8o-l_9&sparams=expire%2Cei%2Cip%2Cid%2Caitags%2Csource%2Crequiressl%2Cgcr%2Cvprv%2Cmime%2Cns%2Cgir%2Cclen%2Cdur%2Clmt&lsparams=mh%2Cmm%2Cmn%2Cms%2Cmv%2Cmvi%2Cpl%2Cinitcwndbps&lsig=AG3C_xAwRQIhAKtJ3joAdGTnZLXoR-xLeWVsQ3pBFOxnMIUHAR2E77jXAiA1qD1yUgq5_CCdC4GDgv4Wd-QA7SuxPeSBHcX1RWfA1A%3D%3D&sig=AOq0QJ8wRgIhAIc5RVmtaWqGDeRhHzlaWZVjHdqv-oa6c1ytfWZZJ4FAAiEAo00Hhx8iJbq5OKWdoSV6gVQnnT9vdC_2x7c1b-CS0ic=", "width": 240, "ext": "mp4", "vcodec": "av01.0.00M.08", "acodec": "none", "vbr": 17.043, "downloader_options": {"http_chunk_size": 10485760}, "container": "mp4_dash", "format": "395 - 240x240 (240p)", "protocol": "https", "http_headers": {"User-Agent": "Mozilla/5.0 (Windows NT 10.0; Win64; x64) AppleWebKit/537.36 (KHTML, like Gecko) Chrome/75.0.3757.0 Safari/537.36", "Accept-Charset": "ISO-8859-1,utf-8;q=0.7,*;q=0.7", "Accept": "text/html,application/xhtml+xml,application/xml;q=0.9,*/*;q=0.8", "Accept-Encoding": "gzip, deflate", "Accept-Language": "en-us,en;q=0.5"}}, {"asr": null, "filesize": 17252552, "format_id": "242", "format_note": "240p", "fps": 25, "height": 240, "quality": 1, "tbr": 30.575, "url": "https://rr2---sn-0opoxu-ihv6.googlevideo.com/videoplayback?expire=1670705620&ei=dJ2UY5K0GczCkwbisZKoCA&ip=189.173.225.87&id=o-AGRflb0DCW1x_jnc6XSKjQl4TLRiEQbTQ4W8ZZEJG5MN&itag=242&aitags=133%2C134%2C135%2C136%2C137%2C160%2C242%2C243%2C244%2C247%2C248%2C278%2C394%2C395%2C396%2C397%2C398%2C399&source=youtube&requiressl=yes&mh=U4&mm=31%2C29&mn=sn-0opoxu-ihv6%2Csn-q4flrnez&ms=au%2Crdu&mv=m&mvi=2&pl=24&gcr=mx&initcwndbps=888750&vprv=1&mime=video%2Fwebm&ns=Yg5JUhqLY5KMBKDaV1hgA6sJ&gir=yes&clen=17252552&dur=4514.120&lmt=1614557896865425&mt=1670683760&fvip=3&keepalive=yes&fexp=24001373%2C24007246&beids=24432632&c=WEB&txp=5432434&n=De6OCzL7fIn8o-l_9&sparams=expire%2Cei%2Cip%2Cid%2Caitags%2Csource%2Crequiressl%2Cgcr%2Cvprv%2Cmime%2Cns%2Cgir%2Cclen%2Cdur%2Clmt&lsparams=mh%2Cmm%2Cmn%2Cms%2Cmv%2Cmvi%2Cpl%2Cinitcwndbps&lsig=AG3C_xAwRAIgd0E7pLd2Kw9mnnF2M14Q6NXAX20eo3hmzdkk_TB3CkwCIDSqd2t5Z2rx1tozBrKwdFIxONlFfiQJ6vxvvHZG95U_&sig=AOq0QJ8wRQIhALnaVvWpVlwQZjs0lIHyRhKGPzqCX9aKPFEJZkC9GcYpAiArJHnmdTQnofQ7iJXzuW6sXgbuc28I3UuHozEx7JmORA==", "width": 240, "ext": "webm", "vcodec": "vp9", "acodec": "none", "vbr": 30.575, "downloader_options": {"http_chunk_size": 10485760}, "container": "webm_dash", "format": "242 - 240x240 (240p)", "protocol": "https", "http_headers": {"User-Agent": "Mozilla/5.0 (Windows NT 10.0; Win64; x64) AppleWebKit/537.36 (KHTML, like Gecko) Chrome/75.0.3757.0 Safari/537.36", "Accept-Charset": "ISO-8859-1,utf-8;q=0.7,*;q=0.7", "Accept": "text/html,application/xhtml+xml,application/xml;q=0.9,*/*;q=0.8", "Accept-Encoding": "gzip, deflate", "Accept-Language": "en-us,en;q=0.5"}}, {"asr": null, "filesize": 10031786, "format_id": "134", "format_note": "360p", "fps": 25, "height": 360, "quality": 2, "tbr": 17.778, "url": "https://rr2---sn-0opoxu-ihv6.googlevideo.com/videoplayback?expire=1670705620&ei=dJ2UY5K0GczCkwbisZKoCA&ip=189.173.225.87&id=o-AGRflb0DCW1x_jnc6XSKjQl4TLRiEQbTQ4W8ZZEJG5MN&itag=134&aitags=133%2C134%2C135%2C136%2C137%2C160%2C242%2C243%2C244%2C247%2C248%2C278%2C394%2C395%2C396%2C397%2C398%2C399&source=youtube&requiressl=yes&mh=U4&mm=31%2C29&mn=sn-0opoxu-ihv6%2Csn-q4flrnez&ms=au%2Crdu&mv=m&mvi=2&pl=24&gcr=mx&initcwndbps=888750&vprv=1&mime=video%2Fmp4&ns=Yg5JUhqLY5KMBKDaV1hgA6sJ&gir=yes&clen=10031786&dur=4514.120&lmt=1614557576072352&mt=1670683760&fvip=3&keepalive=yes&fexp=24001373%2C24007246&beids=24432632&c=WEB&txp=5432434&n=De6OCzL7fIn8o-l_9&sparams=expire%2Cei%2Cip%2Cid%2Caitags%2Csource%2Crequiressl%2Cgcr%2Cvprv%2Cmime%2Cns%2Cgir%2Cclen%2Cdur%2Clmt&lsparams=mh%2Cmm%2Cmn%2Cms%2Cmv%2Cmvi%2Cpl%2Cinitcwndbps&lsig=AG3C_xAwRQIhAPQTPZmK1y7nI8LlxSxG_7DEwRdBooEsSw9KBkiww2UQAiBnvYHSYq8ZuO4W_7ItiS-zVbnB-0Bswm9PrKWzGVdYZw%3D%3D&sig=AOq0QJ8wRgIhAJiXX3R48ZuvqrizAbHV0OnkJHh_QO4pV4fD64l07MiDAiEAzRgyeg0pBQfZOyM7kV7K2uGiIDY9Hw9Ln1276VsUcaE=", "width": 360, "ext": "mp4", "vcodec": "avc1.4d4015", "acodec": "none", "vbr": 17.778, "downloader_options": {"http_chunk_size": 10485760}, "container": "mp4_dash", "format": "134 - 360x360 (360p)", "protocol": "https", "http_headers": {"User-Agent": "Mozilla/5.0 (Windows NT 10.0; Win64; x64) AppleWebKit/537.36 (KHTML, like Gecko) Chrome/75.0.3757.0 Safari/537.36", "Accept-Charset": "ISO-8859-1,utf-8;q=0.7,*;q=0.7", "Accept": "text/html,application/xhtml+xml,application/xml;q=0.9,*/*;q=0.8", "Accept-Encoding": "gzip, deflate", "Accept-Language": "en-us,en;q=0.5"}}, {"asr": null, "filesize": 16867476, "format_id": "396", "format_note": "360p", "fps": 25, "height": 360, "quality": 2, "tbr": 29.892, "url": "https://rr2---sn-0opoxu-ihv6.googlevideo.com/videoplayback?expire=1670705620&ei=dJ2UY5K0GczCkwbisZKoCA&ip=189.173.225.87&id=o-AGRflb0DCW1x_jnc6XSKjQl4TLRiEQbTQ4W8ZZEJG5MN&itag=396&aitags=133%2C134%2C135%2C136%2C137%2C160%2C242%2C243%2C244%2C247%2C248%2C278%2C394%2C395%2C396%2C397%2C398%2C399&source=youtube&requiressl=yes&mh=U4&mm=31%2C29&mn=sn-0opoxu-ihv6%2Csn-q4flrnez&ms=au%2Crdu&mv=m&mvi=2&pl=24&gcr=mx&initcwndbps=888750&vprv=1&mime=video%2Fmp4&ns=Yg5JUhqLY5KMBKDaV1hgA6sJ&gir=yes&clen=16867476&dur=4514.120&lmt=1615882724593046&mt=1670683760&fvip=3&keepalive=yes&fexp=24001373%2C24007246&beids=24432632&c=WEB&txp=5436432&n=De6OCzL7fIn8o-l_9&sparams=expire%2Cei%2Cip%2Cid%2Caitags%2Csource%2Crequiressl%2Cgcr%2Cvprv%2Cmime%2Cns%2Cgir%2Cclen%2Cdur%2Clmt&lsparams=mh%2Cmm%2Cmn%2Cms%2Cmv%2Cmvi%2Cpl%2Cinitcwndbps&lsig=AG3C_xAwRQIgB_kjmVS1nZC6b-WDpcADV1ZEWUHt8ADN10ODy3xLbXACIQDOGeXpPnRFZnL34sW-mVHbWb6qi5cfJmhEKTiQedRbYQ%3D%3D&sig=AOq0QJ8wRAIgeI0hVlpLSl5LlEqr6ivrmMQR647A_mR0mJjkEH0HNtsCIAZTP8is7AyUTZ-K3g8ty1uiIOp-j_2ORmY6a5Ykclv3", "width": 360, "ext": "mp4", "vcodec": "av01.0.00M.08", "acodec": "none", "vbr": 29.892, "downloader_options": {"http_chunk_size": 10485760}, "container": "mp4_dash", "format": "396 - 360x360 (360p)", "protocol": "https", "http_headers": {"User-Agent": "Mozilla/5.0 (Windows NT 10.0; Win64; x64) AppleWebKit/537.36 (KHTML, like Gecko) Chrome/75.0.3757.0 Safari/537.36", "Accept-Charset": "ISO-8859-1,utf-8;q=0.7,*;q=0.7", "Accept": "text/html,application/xhtml+xml,application/xml;q=0.9,*/*;q=0.8", "Accept-Encoding": "gzip, deflate", "Accept-Language": "en-us,en;q=0.5"}}, {"asr": null, "filesize": 28236812, "format_id": "243", "format_note": "360p", "fps": 25, "height": 360, "quality": 2, "tbr": 50.041, "url": "https://rr2---sn-0opoxu-ihv6.googlevideo.com/videoplayback?expire=1670705620&ei=dJ2UY5K0GczCkwbisZKoCA&ip=189.173.225.87&id=o-AGRflb0DCW1x_jnc6XSKjQl4TLRiEQbTQ4W8ZZEJG5MN&itag=243&aitags=133%2C134%2C135%2C136%2C137%2C160%2C242%2C243%2C244%2C247%2C248%2C278%2C394%2C395%2C396%2C397%2C398%2C399&source=youtube&requiressl=yes&mh=U4&mm=31%2C29&mn=sn-0opoxu-ihv6%2Csn-q4flrnez&ms=au%2Crdu&mv=m&mvi=2&pl=24&gcr=mx&initcwndbps=888750&vprv=1&mime=video%2Fwebm&ns=Yg5JUhqLY5KMBKDaV1hgA6sJ&gir=yes&clen=28236812&dur=4514.120&lmt=1614557907998091&mt=1670683760&fvip=3&keepalive=yes&fexp=24001373%2C24007246&beids=24432632&c=WEB&txp=5432434&n=De6OCzL7fIn8o-l_9&sparams=expire%2Cei%2Cip%2Cid%2Caitags%2Csource%2Crequiressl%2Cgcr%2Cvprv%2Cmime%2Cns%2Cgir%2Cclen%2Cdur%2Clmt&lsparams=mh%2Cmm%2Cmn%2Cms%2Cmv%2Cmvi%2Cpl%2Cinitcwndbps&lsig=AG3C_xAwRAIgIkrNMZsjEarhFNh6GBng6BCtEzSyLRLcVyuD-UMEt-UCIFoccFHfsIWwWmMpgEIA6TLjTSyDWGBIjistT2toyiuC&sig=AOq0QJ8wRQIhAP6QQTUoecQvK5W89l0iOXglX5cgD7WlYIBJhPrIVo5iAiBhw6OTR1zadkscyUzID4Jb8CkCGg9v9Ox3yHVfNlTshQ==", "width": 360, "ext": "webm", "vcodec": "vp9", "acodec": "none", "vbr": 50.041, "downloader_options": {"http_chunk_size": 10485760}, "container": "webm_dash", "format": "243 - 360x360 (360p)", "protocol": "https", "http_headers": {"User-Agent": "Mozilla/5.0 (Windows NT 10.0; Win64; x64) AppleWebKit/537.36 (KHTML, like Gecko) Chrome/75.0.3757.0 Safari/537.36", "Accept-Charset": "ISO-8859-1,utf-8;q=0.7,*;q=0.7", "Accept": "text/html,application/xhtml+xml,application/xml;q=0.9,*/*;q=0.8", "Accept-Encoding": "gzip, deflate", "Accept-Language": "en-us,en;q=0.5"}}, {"asr": null, "filesize": 13467106, "format_id": "135", "format_note": "480p", "fps": 25, "height": 480, "quality": 3, "tbr": 23.866, "url": "https://rr2---sn-0opoxu-ihv6.googlevideo.com/videoplayback?expire=1670705620&ei=dJ2UY5K0GczCkwbisZKoCA&ip=189.173.225.87&id=o-AGRflb0DCW1x_jnc6XSKjQl4TLRiEQbTQ4W8ZZEJG5MN&itag=135&aitags=133%2C134%2C135%2C136%2C137%2C160%2C242%2C243%2C244%2C247%2C248%2C278%2C394%2C395%2C396%2C397%2C398%2C399&source=youtube&requiressl=yes&mh=U4&mm=31%2C29&mn=sn-0opoxu-ihv6%2Csn-q4flrnez&ms=au%2Crdu&mv=m&mvi=2&pl=24&gcr=mx&initcwndbps=888750&vprv=1&mime=video%2Fmp4&ns=Yg5JUhqLY5KMBKDaV1hgA6sJ&gir=yes&clen=13467106&dur=4514.120&lmt=1614557581959174&mt=1670683760&fvip=3&keepalive=yes&fexp=24001373%2C24007246&beids=24432632&c=WEB&txp=5432434&n=De6OCzL7fIn8o-l_9&sparams=expire%2Cei%2Cip%2Cid%2Caitags%2Csource%2Crequiressl%2Cgcr%2Cvprv%2Cmime%2Cns%2Cgir%2Cclen%2Cdur%2Clmt&lsparams=mh%2Cmm%2Cmn%2Cms%2Cmv%2Cmvi%2Cpl%2Cinitcwndbps&lsig=AG3C_xAwRAIgGFf57XzUIbj47NYR0jGLuMpJrVunsHCOdGUlcf8OKRYCICYvIoLE-kTInej-APySx0y-9-6gzAKDPoK-VY6RiDZ7&sig=AOq0QJ8wRgIhAL0VehoEaCqjefBftGqs0x5lZTBdpka-gJGYNg27UOcxAiEAza0f6OMHABAV5V8efI2ilm9WTfBjSLacVqWbEDQhghY=", "width": 480, "ext": "mp4", "vcodec": "avc1.4d401e", "acodec": "none", "vbr": 23.866, "downloader_options": {"http_chunk_size": 10485760}, "container": "mp4_dash", "format": "135 - 480x480 (480p)", "protocol": "https", "http_headers": {"User-Agent": "Mozilla/5.0 (Windows NT 10.0; Win64; x64) AppleWebKit/537.36 (KHTML, like Gecko) Chrome/75.0.3757.0 Safari/537.36", "Accept-Charset": "ISO-8859-1,utf-8;q=0.7,*;q=0.7", "Accept": "text/html,application/xhtml+xml,application/xml;q=0.9,*/*;q=0.8", "Accept-Encoding": "gzip, deflate", "Accept-Language": "en-us,en;q=0.5"}}, {"asr": null, "filesize": 26637999, "format_id": "397", "format_note": "480p", "fps": 25, "height": 480, "quality": 3, "tbr": 47.208, "url": "https://rr2---sn-0opoxu-ihv6.googlevideo.com/videoplayback?expire=1670705620&ei=dJ2UY5K0GczCkwbisZKoCA&ip=189.173.225.87&id=o-AGRflb0DCW1x_jnc6XSKjQl4TLRiEQbTQ4W8ZZEJG5MN&itag=397&aitags=133%2C134%2C135%2C136%2C137%2C160%2C242%2C243%2C244%2C247%2C248%2C278%2C394%2C395%2C396%2C397%2C398%2C399&source=youtube&requiressl=yes&mh=U4&mm=31%2C29&mn=sn-0opoxu-ihv6%2Csn-q4flrnez&ms=au%2Crdu&mv=m&mvi=2&pl=24&gcr=mx&initcwndbps=888750&vprv=1&mime=video%2Fmp4&ns=Yg5JUhqLY5KMBKDaV1hgA6sJ&gir=yes&clen=26637999&dur=4514.120&lmt=1615882727934980&mt=1670683760&fvip=3&keepalive=yes&fexp=24001373%2C24007246&beids=24432632&c=WEB&txp=5436432&n=De6OCzL7fIn8o-l_9&sparams=expire%2Cei%2Cip%2Cid%2Caitags%2Csource%2Crequiressl%2Cgcr%2Cvprv%2Cmime%2Cns%2Cgir%2Cclen%2Cdur%2Clmt&lsparams=mh%2Cmm%2Cmn%2Cms%2Cmv%2Cmvi%2Cpl%2Cinitcwndbps&lsig=AG3C_xAwRQIhAKCSz_x0CxA3hJUxHEnlmp9XXiOELsvhBCL2JsiGdHM8AiAE8NAN9kEn_n-s2GmzbvfixomXrhLR6-DdmzoQus-2rw%3D%3D&sig=AOq0QJ8wRQIgKx70AYDcDB0t0LfZwTag0A-LIhFnxdtlnc_jx8bjnMgCIQD3YJWganQAf-oY_xzm-cu0m5P2ilM3GRfdhvmtyiKTLA==", "width": 480, "ext": "mp4", "vcodec": "av01.0.01M.08", "acodec": "none", "vbr": 47.208, "downloader_options": {"http_chunk_size": 10485760}, "container": "mp4_dash", "format": "397 - 480x480 (480p)", "protocol": "https", "http_headers": {"User-Agent": "Mozilla/5.0 (Windows NT 10.0; Win64; x64) AppleWebKit/537.36 (KHTML, like Gecko) Chrome/75.0.3757.0 Safari/537.36", "Accept-Charset": "ISO-8859-1,utf-8;q=0.7,*;q=0.7", "Accept": "text/html,application/xhtml+xml,application/xml;q=0.9,*/*;q=0.8", "Accept-Encoding": "gzip, deflate", "Accept-Language": "en-us,en;q=0.5"}}, {"asr": null, "filesize": 44313208, "format_id": "244", "format_note": "480p", "fps": 25, "height": 480, "quality": 3, "tbr": 78.532, "url": "https://rr2---sn-0opoxu-ihv6.googlevideo.com/videoplayback?expire=1670705620&ei=dJ2UY5K0GczCkwbisZKoCA&ip=189.173.225.87&id=o-AGRflb0DCW1x_jnc6XSKjQl4TLRiEQbTQ4W8ZZEJG5MN&itag=244&aitags=133%2C134%2C135%2C136%2C137%2C160%2C242%2C243%2C244%2C247%2C248%2C278%2C394%2C395%2C396%2C397%2C398%2C399&source=youtube&requiressl=yes&mh=U4&mm=31%2C29&mn=sn-0opoxu-ihv6%2Csn-q4flrnez&ms=au%2Crdu&mv=m&mvi=2&pl=24&gcr=mx&initcwndbps=888750&vprv=1&mime=video%2Fwebm&ns=Yg5JUhqLY5KMBKDaV1hgA6sJ&gir=yes&clen=44313208&dur=4514.120&lmt=1614557911537258&mt=1670683760&fvip=3&keepalive=yes&fexp=24001373%2C24007246&beids=24432632&c=WEB&txp=5432434&n=De6OCzL7fIn8o-l_9&sparams=expire%2Cei%2Cip%2Cid%2Caitags%2Csource%2Crequiressl%2Cgcr%2Cvprv%2Cmime%2Cns%2Cgir%2Cclen%2Cdur%2Clmt&lsparams=mh%2Cmm%2Cmn%2Cms%2Cmv%2Cmvi%2Cpl%2Cinitcwndbps&lsig=AG3C_xAwRQIgNN3iIRtg-NLzasvNe15P0Lws--Z2dzYf1TjYxCcvFnMCIQCnN5Y_DfKr_X_bk3R6w_bJf1Fu8yTq1nb87GypbHzYsg%3D%3D&sig=AOq0QJ8wRQIhAIfyTslK_0mWlvXzIra-uYcVoXOHAjhtSj16xhVI81zlAiBd58xMn91ya1O4CxDa1kCMJUltOnByVWzvaTUCOZfBAg==", "width": 480, "ext": "webm", "vcodec": "vp9", "acodec": "none", "vbr": 78.532, "downloader_options": {"http_chunk_size": 10485760}, "container": "webm_dash", "format": "244 - 480x480 (480p)", "protocol": "https", "http_headers": {"User-Agent": "Mozilla/5.0 (Windows NT 10.0; Win64; x64) AppleWebKit/537.36 (KHTML, like Gecko) Chrome/75.0.3757.0 Safari/537.36", "Accept-Charset": "ISO-8859-1,utf-8;q=0.7,*;q=0.7", "Accept": "text/html,application/xhtml+xml,application/xml;q=0.9,*/*;q=0.8", "Accept-Encoding": "gzip, deflate", "Accept-Language": "en-us,en;q=0.5"}}, {"asr": null, "filesize": 18104555, "format_id": "136", "format_note": "720p", "fps": 25, "height": 720, "quality": 4, "tbr": 32.085, "url": "https://rr2---sn-0opoxu-ihv6.googlevideo.com/videoplayback?expire=1670705620&ei=dJ2UY5K0GczCkwbisZKoCA&ip=189.173.225.87&id=o-AGRflb0DCW1x_jnc6XSKjQl4TLRiEQbTQ4W8ZZEJG5MN&itag=136&aitags=133%2C134%2C135%2C136%2C137%2C160%2C242%2C243%2C244%2C247%2C248%2C278%2C394%2C395%2C396%2C397%2C398%2C399&source=youtube&requiressl=yes&mh=U4&mm=31%2C29&mn=sn-0opoxu-ihv6%2Csn-q4flrnez&ms=au%2Crdu&mv=m&mvi=2&pl=24&gcr=mx&initcwndbps=888750&vprv=1&mime=video%2Fmp4&ns=Yg5JUhqLY5KMBKDaV1hgA6sJ&gir=yes&clen=18104555&dur=4514.120&lmt=1614557576291414&mt=1670683760&fvip=3&keepalive=yes&fexp=24001373%2C24007246&beids=24432632&c=WEB&txp=5432434&n=De6OCzL7fIn8o-l_9&sparams=expire%2Cei%2Cip%2Cid%2Caitags%2Csource%2Crequiressl%2Cgcr%2Cvprv%2Cmime%2Cns%2Cgir%2Cclen%2Cdur%2Clmt&lsparams=mh%2Cmm%2Cmn%2Cms%2Cmv%2Cmvi%2Cpl%2Cinitcwndbps&lsig=AG3C_xAwRQIgKK1lWHH19o5go4IDBJoZ5ITk-YMoqYJmcfs-oa8VrJYCIQCefks2eFBunzySJdxISrlNuu_viPh-KV6oQNM6EuB3qw%3D%3D&sig=AOq0QJ8wRQIhAJ3BpYVkHEmetm7J1ZYZzPpRJcC3SXhdCjiN96UGc7kwAiA9HNGAB15ODU3FjbPydPgtFMkqlZaFcy0KwvbMdh0Usg==", "width": 720, "ext": "mp4", "vcodec": "avc1.4d401f", "acodec": "none", "vbr": 32.085, "downloader_options": {"http_chunk_size": 10485760}, "container": "mp4_dash", "format": "136 - 720x720 (720p)", "protocol": "https", "http_headers": {"User-Agent": "Mozilla/5.0 (Windows NT 10.0; Win64; x64) AppleWebKit/537.36 (KHTML, like Gecko) Chrome/75.0.3757.0 Safari/537.36", "Accept-Charset": "ISO-8859-1,utf-8;q=0.7,*;q=0.7", "Accept": "text/html,application/xhtml+xml,application/xml;q=0.9,*/*;q=0.8", "Accept-Encoding": "gzip, deflate", "Accept-Language": "en-us,en;q=0.5"}}, {"asr": null, "filesize": 45065672, "format_id": "398", "format_note": "720p", "fps": 25, "height": 720, "quality": 4, "tbr": 79.866, "url": "https://rr2---sn-0opoxu-ihv6.googlevideo.com/videoplayback?expire=1670705620&ei=dJ2UY5K0GczCkwbisZKoCA&ip=189.173.225.87&id=o-AGRflb0DCW1x_jnc6XSKjQl4TLRiEQbTQ4W8ZZEJG5MN&itag=398&aitags=133%2C134%2C135%2C136%2C137%2C160%2C242%2C243%2C244%2C247%2C248%2C278%2C394%2C395%2C396%2C397%2C398%2C399&source=youtube&requiressl=yes&mh=U4&mm=31%2C29&mn=sn-0opoxu-ihv6%2Csn-q4flrnez&ms=au%2Crdu&mv=m&mvi=2&pl=24&gcr=mx&initcwndbps=888750&vprv=1&mime=video%2Fmp4&ns=Yg5JUhqLY5KMBKDaV1hgA6sJ&gir=yes&clen=45065672&dur=4514.120&lmt=1615882729121976&mt=1670683760&fvip=3&keepalive=yes&fexp=24001373%2C24007246&beids=24432632&c=WEB&txp=5436432&n=De6OCzL7fIn8o-l_9&sparams=expire%2Cei%2Cip%2Cid%2Caitags%2Csource%2Crequiressl%2Cgcr%2Cvprv%2Cmime%2Cns%2Cgir%2Cclen%2Cdur%2Clmt&lsparams=mh%2Cmm%2Cmn%2Cms%2Cmv%2Cmvi%2Cpl%2Cinitcwndbps&lsig=AG3C_xAwRAIgR50dL1hDRu0da0kVy1OnQav3ItdacJqOrwC0hUurSAYCIFoMGdgnAUDzPyXTG86e2KJwr2hdgbDaxKeRSpXtrxcu&sig=AOq0QJ8wRQIhAIENL550FAqdRLrzDXbLvnb4rHxA2PHGQmgv0YBZHvZjAiAlxnHAsh6b41Dtnc6i45V_KMPH_PDOsMHIBInISDo_jw==", "width": 720, "ext": "mp4", "vcodec": "av01.0.04M.08", "acodec": "none", "vbr": 79.866, "downloader_options": {"http_chunk_size": 10485760}, "container": "mp4_dash", "format": "398 - 720x720 (720p)", "protocol": "https", "http_headers": {"User-Agent": "Mozilla/5.0 (Windows NT 10.0; Win64; x64) AppleWebKit/537.36 (KHTML, like Gecko) Chrome/75.0.3757.0 Safari/537.36", "Accept-Charset": "ISO-8859-1,utf-8;q=0.7,*;q=0.7", "Accept": "text/html,application/xhtml+xml,application/xml;q=0.9,*/*;q=0.8", "Accept-Encoding": "gzip, deflate", "Accept-Language": "en-us,en;q=0.5"}}, {"asr": null, "filesize": 86140527, "format_id": "247", "format_note": "720p", "fps": 25, "height": 720, "quality": 4, "tbr": 152.659, "url": "https://rr2---sn-0opoxu-ihv6.googlevideo.com/videoplayback?expire=1670705620&ei=dJ2UY5K0GczCkwbisZKoCA&ip=189.173.225.87&id=o-AGRflb0DCW1x_jnc6XSKjQl4TLRiEQbTQ4W8ZZEJG5MN&itag=247&aitags=133%2C134%2C135%2C136%2C137%2C160%2C242%2C243%2C244%2C247%2C248%2C278%2C394%2C395%2C396%2C397%2C398%2C399&source=youtube&requiressl=yes&mh=U4&mm=31%2C29&mn=sn-0opoxu-ihv6%2Csn-q4flrnez&ms=au%2Crdu&mv=m&mvi=2&pl=24&gcr=mx&initcwndbps=888750&vprv=1&mime=video%2Fwebm&ns=Yg5JUhqLY5KMBKDaV1hgA6sJ&gir=yes&clen=86140527&dur=4514.120&lmt=1614557927226917&mt=1670683760&fvip=3&keepalive=yes&fexp=24001373%2C24007246&beids=24432632&c=WEB&txp=5432434&n=De6OCzL7fIn8o-l_9&sparams=expire%2Cei%2Cip%2Cid%2Caitags%2Csource%2Crequiressl%2Cgcr%2Cvprv%2Cmime%2Cns%2Cgir%2Cclen%2Cdur%2Clmt&lsparams=mh%2Cmm%2Cmn%2Cms%2Cmv%2Cmvi%2Cpl%2Cinitcwndbps&lsig=AG3C_xAwRgIhAKgS-0T83XLtQiLpOITmdrgrvrt-3-pLqx-LKYdyDQoZAiEArla9A5J77XdXzBfVLvgImsSeruU7jluzsfkBAqVNNWw%3D&sig=AOq0QJ8wRAIgdTsaL7PFRgDNiW8lZs5Yjzt_Sd1-xXtL3zqQzr_24eMCIAmIpXtcNbGjjJiuNoU3lXpOapJRuz48xH2j2m1gRjGU", "width": 720, "ext": "webm", "vcodec": "vp9", "acodec": "none", "vbr": 152.659, "downloader_options": {"http_chunk_size": 10485760}, "container": "webm_dash", "format": "247 - 720x720 (720p)", "protocol": "https", "http_headers": {"User-Agent": "Mozilla/5.0 (Windows NT 10.0; Win64; x64) AppleWebKit/537.36 (KHTML, like Gecko) Chrome/75.0.3757.0 Safari/537.36", "Accept-Charset": "ISO-8859-1,utf-8;q=0.7,*;q=0.7", "Accept": "text/html,application/xhtml+xml,application/xml;q=0.9,*/*;q=0.8", "Accept-Encoding": "gzip, deflate", "Accept-Language": "en-us,en;q=0.5"}}, {"asr": null, "filesize": 46931098, "format_id": "137", "format_note": "1080p", "fps": 25, "height": 1080, "quality": 5, "tbr": 83.172, "url": "https://rr2---sn-0opoxu-ihv6.googlevideo.com/videoplayback?expire=1670705620&ei=dJ2UY5K0GczCkwbisZKoCA&ip=189.173.225.87&id=o-AGRflb0DCW1x_jnc6XSKjQl4TLRiEQbTQ4W8ZZEJG5MN&itag=137&aitags=133%2C134%2C135%2C136%2C137%2C160%2C242%2C243%2C244%2C247%2C248%2C278%2C394%2C395%2C396%2C397%2C398%2C399&source=youtube&requiressl=yes&mh=U4&mm=31%2C29&mn=sn-0opoxu-ihv6%2Csn-q4flrnez&ms=au%2Crdu&mv=m&mvi=2&pl=24&gcr=mx&initcwndbps=888750&vprv=1&mime=video%2Fmp4&ns=Yg5JUhqLY5KMBKDaV1hgA6sJ&gir=yes&clen=46931098&dur=4514.120&lmt=1614557637537320&mt=1670683760&fvip=3&keepalive=yes&fexp=24001373%2C24007246&beids=24432632&c=WEB&txp=5432434&n=De6OCzL7fIn8o-l_9&sparams=expire%2Cei%2Cip%2Cid%2Caitags%2Csource%2Crequiressl%2Cgcr%2Cvprv%2Cmime%2Cns%2Cgir%2Cclen%2Cdur%2Clmt&lsparams=mh%2Cmm%2Cmn%2Cms%2Cmv%2Cmvi%2Cpl%2Cinitcwndbps&lsig=AG3C_xAwRQIgf6DVYFGOtWPwydkKywtukBXVjVqSIdUDLDyxmq29uQwCIQDhOX_89JGRBG71BqARve9DGvHadcnDVg6A5XXlyz7fbQ%3D%3D&sig=AOq0QJ8wRgIhAMWdNcTZ1Fm86SQDVi-vRhauqCVnUgmEGCl-ZgLLgN6qAiEA8cIXUOFOkqwl4WNiG3-UZU-yU6UkmpBcg6vDx7Dg1Vk=", "width": 1080, "ext": "mp4", "vcodec": "avc1.640020", "acodec": "none", "vbr": 83.172, "downloader_options": {"http_chunk_size": 10485760}, "container": "mp4_dash", "format": "137 - 1080x1080 (1080p)", "protocol": "https", "http_headers": {"User-Agent": "Mozilla/5.0 (Windows NT 10.0; Win64; x64) AppleWebKit/537.36 (KHTML, like Gecko) Chrome/75.0.3757.0 Safari/537.36", "Accept-Charset": "ISO-8859-1,utf-8;q=0.7,*;q=0.7", "Accept": "text/html,application/xhtml+xml,application/xml;q=0.9,*/*;q=0.8", "Accept-Encoding": "gzip, deflate", "Accept-Language": "en-us,en;q=0.5"}}, {"asr": null, "filesize": 64748370, "format_id": "399", "format_note": "1080p", "fps": 25, "height": 1080, "quality": 5, "tbr": 114.748, "url": "https://rr2---sn-0opoxu-ihv6.googlevideo.com/videoplayback?expire=1670705620&ei=dJ2UY5K0GczCkwbisZKoCA&ip=189.173.225.87&id=o-AGRflb0DCW1x_jnc6XSKjQl4TLRiEQbTQ4W8ZZEJG5MN&itag=399&aitags=133%2C134%2C135%2C136%2C137%2C160%2C242%2C243%2C244%2C247%2C248%2C278%2C394%2C395%2C396%2C397%2C398%2C399&source=youtube&requiressl=yes&mh=U4&mm=31%2C29&mn=sn-0opoxu-ihv6%2Csn-q4flrnez&ms=au%2Crdu&mv=m&mvi=2&pl=24&gcr=mx&initcwndbps=888750&vprv=1&mime=video%2Fmp4&ns=Yg5JUhqLY5KMBKDaV1hgA6sJ&gir=yes&clen=64748370&dur=4514.120&lmt=1615882737238855&mt=1670683760&fvip=3&keepalive=yes&fexp=24001373%2C24007246&beids=24432632&c=WEB&txp=5436432&n=De6OCzL7fIn8o-l_9&sparams=expire%2Cei%2Cip%2Cid%2Caitags%2Csource%2Crequiressl%2Cgcr%2Cvprv%2Cmime%2Cns%2Cgir%2Cclen%2Cdur%2Clmt&lsparams=mh%2Cmm%2Cmn%2Cms%2Cmv%2Cmvi%2Cpl%2Cinitcwndbps&lsig=AG3C_xAwRgIhAJ1BLwiVb6NjUYqTkiyBoNtmrWyKO0Y-wcP_BF04wyGlAiEA76AwGSCa80HMcNYmzUfXES5A5eFb0t0Uq7TZ-CQSMYo%3D&sig=AOq0QJ8wRQIgYJ12wrR6oS-h648Kjvl1-4R69H13dvtWF6U_GmetHlICIQDedqaoNyBsVLw35Bzy5JDS2o7vlx1YVpFb6RkTTiqsOw==", "width": 1080, "ext": "mp4", "vcodec": "av01.0.08M.08", "acodec": "none", "vbr": 114.748, "downloader_options": {"http_chunk_size": 10485760}, "container": "mp4_dash", "format": "399 - 1080x1080 (1080p)", "protocol": "https", "http_headers": {"User-Agent": "Mozilla/5.0 (Windows NT 10.0; Win64; x64) AppleWebKit/537.36 (KHTML, like Gecko) Chrome/75.0.3757.0 Safari/537.36", "Accept-Charset": "ISO-8859-1,utf-8;q=0.7,*;q=0.7", "Accept": "text/html,application/xhtml+xml,application/xml;q=0.9,*/*;q=0.8", "Accept-Encoding": "gzip, deflate", "Accept-Language": "en-us,en;q=0.5"}}, {"asr": null, "filesize": 154412679, "format_id": "248", "format_note": "1080p", "fps": 25, "height": 1080, "quality": 5, "tbr": 273.652, "url": "https://rr2---sn-0opoxu-ihv6.googlevideo.com/videoplayback?expire=1670705620&ei=dJ2UY5K0GczCkwbisZKoCA&ip=189.173.225.87&id=o-AGRflb0DCW1x_jnc6XSKjQl4TLRiEQbTQ4W8ZZEJG5MN&itag=248&aitags=133%2C134%2C135%2C136%2C137%2C160%2C242%2C243%2C244%2C247%2C248%2C278%2C394%2C395%2C396%2C397%2C398%2C399&source=youtube&requiressl=yes&mh=U4&mm=31%2C29&mn=sn-0opoxu-ihv6%2Csn-q4flrnez&ms=au%2Crdu&mv=m&mvi=2&pl=24&gcr=mx&initcwndbps=888750&vprv=1&mime=video%2Fwebm&ns=Yg5JUhqLY5KMBKDaV1hgA6sJ&gir=yes&clen=154412679&dur=4514.120&lmt=1614557624851554&mt=1670683760&fvip=3&keepalive=yes&fexp=24001373%2C24007246&beids=24432632&c=WEB&txp=5432434&n=De6OCzL7fIn8o-l_9&sparams=expire%2Cei%2Cip%2Cid%2Caitags%2Csource%2Crequiressl%2Cgcr%2Cvprv%2Cmime%2Cns%2Cgir%2Cclen%2Cdur%2Clmt&lsparams=mh%2Cmm%2Cmn%2Cms%2Cmv%2Cmvi%2Cpl%2Cinitcwndbps&lsig=AG3C_xAwRAIgbDVNGgwECzhqEstJF3IwfEwsoKB-xAEFMRlII5H1FqsCIERuOkjCpLoGbnp2X1HjnqBrIlypZbjuydvYTwe-8NYU&sig=AOq0QJ8wRAIgJ_2tTMz6xpcjPojp43cGs4BDwljLWXmOToSq1o902DICIEfeAXtB012ZFnUKXM7nkXGEE_YQHy2qNnTwoa8ZTHL2", "width": 1080, "ext": "webm", "vcodec": "vp9", "acodec": "none", "vbr": 273.652, "downloader_options": {"http_chunk_size": 10485760}, "container": "webm_dash", "format": "248 - 1080x1080 (1080p)", "protocol": "https", "http_headers": {"User-Agent": "Mozilla/5.0 (Windows NT 10.0; Win64; x64) AppleWebKit/537.36 (KHTML, like Gecko) Chrome/75.0.3757.0 Safari/537.36", "Accept-Charset": "ISO-8859-1,utf-8;q=0.7,*;q=0.7", "Accept": "text/html,application/xhtml+xml,application/xml;q=0.9,*/*;q=0.8", "Accept-Encoding": "gzip, deflate", "Accept-Language": "en-us,en;q=0.5"}}, {"asr": 44100, "filesize": null, "format_id": "18", "format_note": "360p", "fps": 25, "height": 360, "quality": 2, "tbr": 146.701, "url": "https://rr2---sn-0opoxu-ihv6.googlevideo.com/videoplayback?expire=1670705620&ei=dJ2UY5K0GczCkwbisZKoCA&ip=189.173.225.87&id=o-AGRflb0DCW1x_jnc6XSKjQl4TLRiEQbTQ4W8ZZEJG5MN&itag=18&source=youtube&requiressl=yes&mh=U4&mm=31%2C29&mn=sn-0opoxu-ihv6%2Csn-q4flrnez&ms=au%2Crdu&mv=m&mvi=2&pl=24&gcr=mx&initcwndbps=888750&vprv=1&mime=video%2Fmp4&ns=R6r4Oti6rz_8zPsoeHiVQokJ&cnr=14&ratebypass=yes&dur=4514.191&lmt=1664747783476429&mt=1670683760&fvip=3&fexp=24001373%2C24007246&beids=24432632&c=WEB&txp=5438434&n=etPN-E2i2M5NLepyn&sparams=expire%2Cei%2Cip%2Cid%2Citag%2Csource%2Crequiressl%2Cgcr%2Cvprv%2Cmime%2Cns%2Ccnr%2Cratebypass%2Cdur%2Clmt&lsparams=mh%2Cmm%2Cmn%2Cms%2Cmv%2Cmvi%2Cpl%2Cinitcwndbps&lsig=AG3C_xAwRQIgETrFmzLKxSYlIpWOJv5DxoPMLGuiHxx8fgSo_Z5qstYCIQCfVJRC0dzvR-8Ssbfs-9aooMSJBdkxIoRzUuX1_wYJ3A%3D%3D&sig=AOq0QJ8wRAIgG_2Zh1FGfNQslj8AwBPoZiY_PKz1PcgXp-liyqWrkBsCIHo_x0NBV0Xe2QTkhFgPgMIFi8MC83jq-Hd71fkQV_Jf", "width": 360, "ext": "mp4", "vcodec": "avc1.42001E", "acodec": "mp4a.40.2", "format": "18 - 360x360 (360p)", "protocol": "https", "http_headers": {"User-Agent": "Mozilla/5.0 (Windows NT 10.0; Win64; x64) AppleWebKit/537.36 (KHTML, like Gecko) Chrome/75.0.3757.0 Safari/537.36", "Accept-Charset": "ISO-8859-1,utf-8;q=0.7,*;q=0.7", "Accept": "text/html,application/xhtml+xml,application/xml;q=0.9,*/*;q=0.8", "Accept-Encoding": "gzip, deflate", "Accept-Language": "en-us,en;q=0.5"}}], "thumbnails": [{"height": 94, "url": "https://i.ytimg.com/vi/tF7ZkPewwQo/hqdefault.jpg?sqp=-oaymwEbCKgBEF5IVfKriqkDDggBFQAAiEIYAXABwAEG&rs=AOn4CLBZTeIW0KEkk5jnRDgO59bIl36JvQ", "width": 168, "resolution": "168x94", "id": "0"}, {"height": 110, "url": "https://i.ytimg.com/vi/tF7ZkPewwQo/hqdefault.jpg?sqp=-oaymwEbCMQBEG5IVfKriqkDDggBFQAAiEIYAXABwAEG&rs=AOn4CLBnVqsJAf16BLLJP86HARYtforFUg", "width": 196, "resolution": "196x110", "id": "1"}, {"height": 138, "url": "https://i.ytimg.com/vi/tF7ZkPewwQo/hqdefault.jpg?sqp=-oaymwEcCPYBEIoBSFXyq4qpAw4IARUAAIhCGAFwAcABBg==&rs=AOn4CLD1BnuLADWDRXbXgSZ9aqNPlJ9NjQ", "width": 246, "resolution": "246x138", "id": "2"}, {"height": 188, "url": "https://i.ytimg.com/vi/tF7ZkPewwQo/hqdefault.jpg?sqp=-oaymwEcCNACELwBSFXyq4qpAw4IARUAAIhCGAFwAcABBg==&rs=AOn4CLAp8Gr0MUoTaE7AFCC770GZ5pq_zg", "width": 336, "resolution": "336x188", "id": "3"}, {"height": 1080, "url": "https://i.ytimg.com/vi_webp/tF7ZkPewwQo/maxresdefault.webp", "width": 1920, "resolution": "1920x1080", "id": "4"}], "description": "Provided to YouTube by Believe SAS\n\nOrquesta Aragon Medley: El Bodeguero / Chaleco / Sabrosona / Al Vaiven de Mi Carreta / Los Tinosos / Bombon Cha / Senor Juez / Calculadora / El Organillero / Los Fantasmas / Yo Tengo una Muneca / No Me Molesto / Silencio / Ay! Jos\u00e9 / La Gloria Eres Tu / N \u00b7 Orquesta Aragon \u00b7 Orquesta Aragon \u00b7 Orquesta Aragon\n\nOrquesta Aragon Medley: El Bodeguero / Chaleco / Sabrosona / Al Vaiven de Mi Carreta / Los Tinosos / Bombon Cha / Senor Juez / Calculadora / El Organillero / Los Fantasmas / Yo Tengo una Muneca / No Me Molesto / Silencio / Ay! Jos\u00e9 / La Gloria Eres Tu / N\n\n\u2117 JB Production\n\nReleased on: 2018-09-24\n\nAuto-generated by YouTube.", "upload_date": "20180925", "uploader": "Orquesta Arag\u00f3n - Topic", "uploader_id": "UCU53USCcK3bAtu5en6iJJjg", "uploader_url": "http://www.youtube.com/channel/UCU53USCcK3bAtu5en6iJJjg", "channel_id": "UCU53USCcK3bAtu5en6iJJjg", "channel_url": "https://www.youtube.com/channel/UCU53USCcK3bAtu5en6iJJjg", "duration": 4514, "view_count": 972776, "average_rating": null, "age_limit": 0, "webpage_url": "https://www.youtube.com/watch?v=tF7ZkPewwQo", "categories": ["Music"], "tags": ["Orquesta Aragon", "Orquesta Aragon Medley: El Bodeguero / Chaleco / Sabrosona / Al Vaiven de Mi Carreta / Los Tinosos / Bombon Cha / Senor Juez / Calculadora / El Organillero / Los Fantasmas / Yo Tengo una Muneca / No Me Molesto / Silencio / Ay! Jos\u00e9 / La Gloria Eres Tu / N"], "is_live": null, "album": "Orquesta Aragon Medley: El Bodeguero / Chaleco / Sabrosona / Al Vaiven de Mi Carreta / Los Tinosos / Bombon Cha / Senor Juez / Calculadora / El Organillero / Los Fantasmas / Yo Tengo una Muneca / No Me Molesto / Silencio / Ay! Jos\u00e9 / La Gloria Eres Tu / N", "artist": "Orquesta Aragon, Orquesta Aragon, Orquesta Aragon", "track": "Orquesta Aragon Medley: El Bodeguero / Chaleco / Sabrosona / Al Vaiven de Mi Carreta / Los Tinosos / Bombon Cha / Senor Juez / Calculadora / El Organillero / Los Fantasmas / Yo Tengo una Muneca / No Me Molesto / Silencio / Ay! Jos\u00e9 / La Gloria Eres Tu / N", "release_date": "20180924", "release_year": 2018, "channel": "Orquesta Arag\u00f3n Official", "creator": "Orquesta Aragon, Orquesta Aragon, Orquesta Aragon", "alt_title": "Orquesta Aragon Medley: El Bodeguero / Chaleco / Sabrosona / Al Vaiven de Mi Carreta / Los Tinosos / Bombon Cha / Senor Juez / Calculadora / El Organillero / Los Fantasmas / Yo Tengo una Muneca / No Me Molesto / Silencio / Ay! Jos\u00e9 / La Gloria Eres Tu / N", "extractor": "youtube", "webpage_url_basename": "watch", "extractor_key": "Youtube", "playlist": null, "playlist_index": null, "thumbnail": "https://i.ytimg.com/vi_webp/tF7ZkPewwQo/maxresdefault.webp", "display_id": "tF7ZkPewwQo", "asr": 44100, "filesize": null, "format_id": "18", "format_note": "360p", "fps": 25, "height": 360, "quality": 2, "tbr": 146.701, "url": "https://rr2---sn-0opoxu-ihv6.googlevideo.com/videoplayback?expire=1670705620&ei=dJ2UY5K0GczCkwbisZKoCA&ip=189.173.225.87&id=o-AGRflb0DCW1x_jnc6XSKjQl4TLRiEQbTQ4W8ZZEJG5MN&itag=18&source=youtube&requiressl=yes&mh=U4&mm=31%2C29&mn=sn-0opoxu-ihv6%2Csn-q4flrnez&ms=au%2Crdu&mv=m&mvi=2&pl=24&gcr=mx&initcwndbps=888750&vprv=1&mime=video%2Fmp4&ns=R6r4Oti6rz_8zPsoeHiVQokJ&cnr=14&ratebypass=yes&dur=4514.191&lmt=1664747783476429&mt=1670683760&fvip=3&fexp=24001373%2C24007246&beids=24432632&c=WEB&txp=5438434&n=etPN-E2i2M5NLepyn&sparams=expire%2Cei%2Cip%2Cid%2Citag%2Csource%2Crequiressl%2Cgcr%2Cvprv%2Cmime%2Cns%2Ccnr%2Cratebypass%2Cdur%2Clmt&lsparams=mh%2Cmm%2Cmn%2Cms%2Cmv%2Cmvi%2Cpl%2Cinitcwndbps&lsig=AG3C_xAwRQIgETrFmzLKxSYlIpWOJv5DxoPMLGuiHxx8fgSo_Z5qstYCIQCfVJRC0dzvR-8Ssbfs-9aooMSJBdkxIoRzUuX1_wYJ3A%3D%3D&sig=AOq0QJ8wRAIgG_2Zh1FGfNQslj8AwBPoZiY_PKz1PcgXp-liyqWrkBsCIHo_x0NBV0Xe2QTkhFgPgMIFi8MC83jq-Hd71fkQV_Jf", "width": 360, "ext": "mp4", "vcodec": "avc1.42001E", "acodec": "mp4a.40.2", "format": "18 - 360x360 (360p)", "protocol": "https", "http_headers": {"User-Agent": "Mozilla/5.0 (Windows NT 10.0; Win64; x64) AppleWebKit/537.36 (KHTML, like Gecko) Chrome/75.0.3757.0 Safari/537.36", "Accept-Charset": "ISO-8859-1,utf-8;q=0.7,*;q=0.7", "Accept": "text/html,application/xhtml+xml,application/xml;q=0.9,*/*;q=0.8", "Accept-Encoding": "gzip, deflate", "Accept-Language": "en-us,en;q=0.5"}, "fulltitle": "Orquesta Aragon Medley: El Bodeguero / Chaleco / Sabrosona / Al Vaiven de Mi Carreta / Los...", "_filename": "Orquesta Aragon Medley - El Bodeguero _ Chaleco _ Sabrosona _ Al Vaiven de Mi Carreta _ Los...-tF7ZkPewwQo.mp4"}